QuantumBlink/QuantumBlink.py
QuantumBlink/__init__.py
QuantumBlink-1.0.2.dist-info/LICENSE
QuantumBlink-1.0.2.dist-info/METADATA
QuantumBlink-1.0.2.dist-info/WHEEL
QuantumBlink-1.0.2.dist-info/top_level.txt
QuantumBlink-1.0.2.dist-info/RECORD
